funfedi_connect/__init__.py
funfedi_connect/__main__.py
funfedi_connect/version.py
funfedi_connect/applications/__init__.py
funfedi_connect/applications/test_init.py
funfedi_connect/applications/webfinger_only.py
funfedi_connect/applications/cattle_grid/__init__.py
funfedi_connect/applications/cattle_grid/api.py
funfedi_connect/applications/cattle_grid/object_getter_class.py
funfedi_connect/applications/friendica/__init__.py
funfedi_connect/applications/friendica/api.py
funfedi_connect/applications/friendica/object_getter_class.py
funfedi_connect/applications/gancio/__init__.py
funfedi_connect/applications/gancio/event_retriever.py
funfedi_connect/applications/lemmy/__init__.py
funfedi_connect/applications/lemmy/object_getter_class.py
funfedi_connect/applications/mastodon/__init__.py
funfedi_connect/applications/mastodon/api.py
funfedi_connect/applications/mastodon/object_getter_class.py
funfedi_connect/applications/misskey/__init__.py
funfedi_connect/applications/misskey/api.py
funfedi_connect/applications/misskey/object_getter_class.py
funfedi_connect/applications/mitra/__init__.py
funfedi_connect/applications/pyfedi/__init__.py
funfedi_connect/applications/pyfedi/object_getter_class.py
funfedi_connect/types/__init__.py
funfedi_connect/types/feature.py
funfedi_connect/types/parsing.py
funfedi_connect-0.2.0.dist-info/METADATA
funfedi_connect-0.2.0.dist-info/WHEEL
funfedi_connect-0.2.0.dist-info/RECORD
