Metadata-Version: 2.4
Name: funfedi_connect
Version: 0.2.0
Project-URL: repository, https://codeberg.org/funfedidev/funfedi_connect
Project-URL: documentation, https://funfedidev.codeberg.page/funfedi_connect/
Requires-Python: >=3.11
Requires-Dist: allure-behave>=2.15.2
Requires-Dist: behave-auto-docstring>=0.1.2
Requires-Dist: click>=8.3.1
Requires-Dist: fediverse-pasture>=0.2.25
Requires-Dist: jsonschema>=4.25.1
